dnadb/__init__.py
dnadb/__main__.py
dnadb/db.py
dnadb/dna.py
dnadb/fasta.new.py
dnadb/fasta.py
dnadb/fastq.py
dnadb/sample.py
dnadb/taxonomy.py
dnadb/types.py
dnadb/utils.py
dnadb/cli/__init__.py
dnadb/cli/fasta.py
dnadb/cli/taxonomy.py
dnadb/integration/__init__.py
dnadb/integration/tf/__init__.py
dnadb/integration/tf/dna.py
dnadb-0.14.2.dist-info/licenses/LICENSE
dnadb-0.14.2.dist-info/METADATA
dnadb-0.14.2.dist-info/WHEEL
dnadb-0.14.2.dist-info/entry_points.txt
dnadb-0.14.2.dist-info/top_level.txt
dnadb-0.14.2.dist-info/RECORD
