Metadata-Version: 2.4
Name: dnadb
Version: 0.14.2
Summary: A library for handling DNA files.
Author-email: David Ludwig <davidludwigii@gmail.com>
License: MIT License
Project-URL: Homepage, https://github.com/DLii-Research/dnadb
Project-URL: Bug Tracker, https://github.com/DLii-Research/dnadb/issues
Classifier: Programming Language :: Python :: 3
Classifier: License :: OSI Approved :: MIT License
Classifier: Operating System :: OS Independent
Requires-Python: >=3.8
License-File: LICENSE
Requires-Dist: lmdbm-lockable>=0.0.5
Requires-Dist: sortedcontainers>=2.4.0
Dynamic: license-file
